heatmapcalc-0.1.9.dist-info/METADATA
heatmapcalc-0.1.9.dist-info/WHEEL
heatmapcalc/__init__.py
heatmapcalc/heatmapcalc.cpython-312-x86_64-linux-gnu.so
heatmapcalc-0.1.9.dist-info/RECORD
